yangsuite_devices-2.9.14.dist-info/licenses/LICENSE.txt
ysdevices/__init__.py
ysdevices/_version.py
ysdevices/apps.py
ysdevices/devprofile.py
ysdevices/plugin.py
ysdevices/urls.py
ysdevices/utilities.py
ysdevices/views.py
ysdevices/static/ysdevices/css/device.css
ysdevices/static/ysdevices/docs/.buildinfo
ysdevices/static/ysdevices/docs/devices.fjson
ysdevices/static/ysdevices/docs/devices.html
ysdevices/static/ysdevices/docs/environment.pickle
ysdevices/static/ysdevices/docs/genindex.fjson
ysdevices/static/ysdevices/docs/genindex.html
ysdevices/static/ysdevices/docs/globalcontext.json
ysdevices/static/ysdevices/docs/index.fjson
ysdevices/static/ysdevices/docs/index.html
ysdevices/static/ysdevices/docs/last_build
ysdevices/static/ysdevices/docs/objects.inv
ysdevices/static/ysdevices/docs/search.fjson
ysdevices/static/ysdevices/docs/search.html
ysdevices/static/ysdevices/docs/searchindex.js
ysdevices/static/ysdevices/docs/searchindex.json
ysdevices/static/ysdevices/docs/tls-ssl.fjson
ysdevices/static/ysdevices/docs/tls-ssl.html
ysdevices/static/ysdevices/docs/.doctrees/devices.doctree
ysdevices/static/ysdevices/docs/.doctrees/environment.pickle
ysdevices/static/ysdevices/docs/.doctrees/index.doctree
ysdevices/static/ysdevices/docs/.doctrees/tls-ssl.doctree
ysdevices/static/ysdevices/docs/_sources/devices.rst.txt
ysdevices/static/ysdevices/docs/_sources/index.rst.txt
ysdevices/static/ysdevices/docs/_sources/tls-ssl.rst.txt
ysdevices/static/ysdevices/docs/_static/basic.css
ysdevices/static/ysdevices/docs/_static/doctools.js
ysdevices/static/ysdevices/docs/_static/documentation_options.js
ysdevices/static/ysdevices/docs/_static/file.png
ysdevices/static/ysdevices/docs/_static/language_data.js
ysdevices/static/ysdevices/docs/_static/minus.png
ysdevices/static/ysdevices/docs/_static/plus.png
ysdevices/static/ysdevices/docs/_static/pygments.css
ysdevices/static/ysdevices/docs/_static/searchtools.js
ysdevices/static/ysdevices/docs/_static/sphinx_highlight.js
ysdevices/static/ysdevices/docs/_static/css/badge_only.css
yangsuite_devices-2.9.14.dist-info/METADATA
yangsuite_devices-2.9.14.dist-info/WHEEL
yangsuite_devices-2.9.14.dist-info/entry_points.txt
yangsuite_devices-2.9.14.dist-info/top_level.txt
yangsuite_devices-2.9.14.dist-info/RECORD
