Metadata-Version: 2.4
Name: yangsuite-devices
Version: 2.9.14
Summary: Device profile definition and management for YANG Suite
Home-page: https://developer.cisco.com/yangsuite
Author: Michael Ott
Author-email: yangsuite-support-ext@cisco.com
License: Cisco End User License Agreement
Requires-Python: >=3.7
License-File: LICENSE.txt
Requires-Dist: yangsuite>=3.0.0
Requires-Dist: yangsuite-filemanager
Requires-Dist: yangsuite-netconf
Dynamic: author
Dynamic: author-email
Dynamic: description
Dynamic: home-page
Dynamic: license
Dynamic: license-file
Dynamic: requires-dist
Dynamic: requires-python
Dynamic: summary
